sodirac/__init__.py
sodirac/_version.py
sodirac/adj.py
sodirac/dataprep.py
sodirac/hyper.py
sodirac/main.py
sodirac/model.py
sodirac/simulations.py
sodirac/trainer.py
sodirac/utils.py
sodirac-0.1.7.dist-info/licenses/LICENSE
sodirac-0.1.7.dist-info/METADATA
sodirac-0.1.7.dist-info/WHEEL
sodirac-0.1.7.dist-info/top_level.txt
sodirac-0.1.7.dist-info/RECORD
