Metadata-Version: 2.4
Name: sodirac
Version: 0.1.7
Summary: Domain Invariant Representation through Adversarial Calibration (DIRAC), a graph neural network to integrate spatial multi-omic data into a unified domain 
Home-page: https://github.com/EsdenRun/DIRAC
Author: XU CHANG
Author-email: changxu@nus.edu.sg
License: MIT
Classifier: Programming Language :: Python :: 3
Classifier: License :: OSI Approved :: MIT License
Classifier: Operating System :: OS Independent
Requires-Python: >=3.9
License-File: LICENSE
Requires-Dist: scanpy==1.10.3
Requires-Dist: igraph==0.11.8
Requires-Dist: leidenalg
Dynamic: author
Dynamic: classifier
Dynamic: description
Dynamic: description-content-type
Dynamic: home-page
Dynamic: license
Dynamic: license-file
Dynamic: requires-dist
Dynamic: requires-python
Dynamic: summary
